sayou/stock/main.py
sayou/stock/version.py
sayou/stock/base/__init__.py
sayou/stock/base/client.py
sayou/stock/base/models.py
sayou/stock/base/parsers/__init__.py
sayou/stock/base/parsers/parser.py
sayou/stock/edgar/README.md
sayou/stock/edgar/__init__.py
sayou/stock/edgar/client.py
sayou/stock/edgar/crawler.py
sayou/stock/edgar/models.py
sayou/stock/edgar/utils.py
sayou/stock/edgar/parsers/__init__.py
sayou/stock/edgar/parsers/def14a.py
sayou/stock/edgar/parsers/form_10k.py
sayou/stock/edgar/parsers/form_13f.py
sayou/stock/edgar/parsers/form_8k.py
sayou/stock/fnguide/README.md
sayou/stock/fnguide/__init__.py
sayou/stock/fnguide/client.py
sayou/stock/fnguide/crawler.py
sayou/stock/fnguide/models.py
sayou/stock/fnguide/utils.py
sayou/stock/fnguide/parsers/__init__.py
sayou/stock/fnguide/parsers/company.py
sayou/stock/fnguide/parsers/comparison.py
sayou/stock/fnguide/parsers/consensus.py
sayou/stock/fnguide/parsers/dart.py
sayou/stock/fnguide/parsers/disclosure.py
sayou/stock/fnguide/parsers/finance.py
sayou/stock/fnguide/parsers/finance_ratio.py
sayou/stock/fnguide/parsers/industry_analysis.py
sayou/stock/fnguide/parsers/invest.py
sayou/stock/fnguide/parsers/json_parser.py
sayou/stock/fnguide/parsers/main.py
sayou/stock/fnguide/parsers/share_analysis.py
sayou/stock/fnguide/parsers/tables.py
sayou/stock/kisrating/README.md
sayou/stock/kisrating/__init__.py
sayou/stock/kisrating/client.py
sayou/stock/kisrating/crawler.py
sayou/stock/kisrating/models.py
sayou/stock/kisrating/parsers/__init__.py
sayou/stock/kisrating/parsers/html_extractor.py
sayou/stock/kisrating/parsers/statistics.py
sayou/stock/kisrating/utils/storage.py
sayou/stock/kisrating/utils/utils.py
sayou/stock/koreainvestment/README.md
sayou/stock/koreainvestment/__init__.py
sayou/stock/koreainvestment/client.py
sayou/stock/koreainvestment/client_.py
sayou/stock/koreainvestment/crawler.py
sayou/stock/koreainvestment/models/__init__.py
sayou/stock/koreainvestment/models/base_model.py
sayou_stock-0.2.11.dist-info/METADATA
sayou_stock-0.2.11.dist-info/WHEEL
sayou_stock-0.2.11.dist-info/licenses/LICENSE
sayou_stock-0.2.11.dist-info/RECORD
