Metadata-Version: 2.4
Name: sayou-stock
Version: 0.2.11
Summary: Sayou Stock Package for Financial Data from SEC, FnGuide, Naver, OpenDART, Yahoo, Korean Investment Securities
Project-URL: Homepage, https://www.sayouzone.com/
Project-URL: Repository, https://github.com/sayouzone/sayou-fabric/tree/main/packages-dev/sayou-stock
Author-email: Sayouzone <support@sayouzone.com>
License:                                  Apache License
License-File: LICENSE
Classifier: License :: OSI Approved :: Apache Software License
Classifier: Operating System :: OS Independent
Classifier: Programming Language :: Python :: 3.9
Classifier: Programming Language :: Python :: 3.10
Classifier: Programming Language :: Python :: 3.11
Classifier: Programming Language :: Python :: 3.12
Classifier: Topic :: Software Development :: Libraries :: Application Frameworks
Requires-Python: >=3.9
Requires-Dist: beautifulsoup4>=4.14.0
Requires-Dist: lxml>=6.0.0
Requires-Dist: pandas>=2.3.3
Requires-Dist: xmltodict>=1.0.0
